HA.v
module HA(A,B,Cout,Sum);

input A,B;
output Sum,Cout;

and a1(Cout,A,B);
xor o1(Sum,A,B);

endmodule

ha_tb2.v
`include "HA.v"
module ha_tb;
reg A,B;
`ifdef T2
reg clk;
`endif
wire Cout,Sum;

HA HA1(A,B,Cout,Sum);

initial 
begin
$dumpfile("ha.vcd");
$dumpvars(0,HA1);
end
`ifdef T1
initial
begin
#10  A=0; B=0;
#10 $display($time, " %b+%b=%b%b",A,B,Cout,Sum);
if (Sum==0 && Cout==0);
else $display("failed");
A=0; B=1; 
#10 $display($time, " %b+%b=%b%b",A,B,Cout,Sum);
if (Sum==1 && Cout==0);
else $display("failed");
A=1; B=0;
#10$display($time, " %b+%b=%b%b",A,B,Cout,Sum);
if (Sum==1 && Cout==0);
else $display("failed");
 A=1; B=1;
#10 $display($time, " %b+%b=%b%b",A,B,Cout,Sum);
if (Sum==0 && Cout==1);
else $display("failed. Expected '10' and got %b%b",Cout,Sum );
#10 $finish;
end

`elsif T2
initial
begin
A=0;
B=0;
clk=0;
forever #10 clk=~clk;
end

initial
begin
    repeat(10)@(posedge clk)
    begin
    A=$random;
    B=$random;   
    end
#200 $finish;
end
initial
begin
    $monitor("%b+%b = %b%b", A,B,Cout,Sum);
end
`else
initial
$display("NO COMPILER DIRECTIVE");

`endif
endmodule

ha.vcd
$date
	Thu Nov  5 20:02:33 2020
$end
$version
	Icarus Verilog
$end
$timescale
	1s
$end
$scope module ha_tb $end
$scope module HA1 $end
$var wire 1 ! A $end
$var wire 1 " B $end
$var wire 1 # Cout $end
$var wire 1 $ Sum $end
$upscope $end
$upscope $end
$enddefinitions $end
#0
$dumpvars
0$
1#
0"
0!
$end
#10
1$
1"
#30
0#
0$
1!
#70
1#
1$
0"
#90
0#
0$
1"
#110
1#
1$
0!
#130
0"
1!
#190
0#
0$
1"
