HA.v
module HA(A,B,Cout,Sum);

input A,B;
output Sum,Cout;

and a1(Cout,A,B);
xor o1(Sum,A,B);

endmodule

ha_tb1.v
`include "HA.v"
module ha_tb;
reg A,B;
reg clk;
wire Cout,Sum;

HA HA1(A,B,Cout,Sum);

initial 
begin
$dumpfile("ha.vcd");
$dumpvars(0,HA1);
end

initial
begin
A=0;
B=0;
clk=0;
forever #10 clk=~clk;
end

initial
begin
    repeat(10)@(posedge clk)
    begin
    A=$random;
    B=$random;   
    end
#200 $finish;
end

initial
begin
    $monitor("%b+%b = %b%b", A,B,Cout,Sum);
end

endmodule

ha.vcd
$date
	Thu Nov  5 19:31:16 2020
$end
$version
	Icarus Verilog
$end
$timescale
	1s
$end
$scope module ha_tb $end
$scope module HA1 $end
$var wire 1 ! A $end
$var wire 1 " B $end
$var wire 1 # Cout $end
$var wire 1 $ Sum $end
$upscope $end
$upscope $end
$enddefinitions $end
#0
$dumpvars
0$
0#
0"
0!
$end
#10
1$
1"
#30
1#
0$
1!
#70
0#
1$
0"
#90
1#
0$
1"
#110
0#
1$
0!
#130
0"
1!
#190
1#
0$
1"
