RCA/FA.v
module FA (a,b,cin,sum,cout);
	input a, b, cin;
	output sum, cout;

	assign sum = cin ^ a ^ b; 
	assign cout = (a & b) | (b & cin) | (a & cin); 
endmodule

RCA/RCA_4.v
`include "FA.v"
module RCA_4 (a,b,cin,sum,cout);
	input [3:0] a, b; 
	input cin;
	output [3:0] sum; 
	output cout;
	wire w[2:0];
	FA	FA0(a[0],b[0],cin,sum[0],w[0]);
	FA	FA1(a[1],b[1],w[0],sum[1],w[1]);
	FA	FA2(a[2],b[2],w[1],sum[2],w[2]);
	FA	FA3(a[3],b[3],w[2],sum[3],cout);	
endmodule

RCA/RCA_4_tb_all.v
`include "RCA_4.v"
module RCA_4_tb;
parameter N=4;
reg [N-1:0] a, b;
reg cin;
wire [N-1:0] sum; 
wire cout;

integer k = (2**N)*(2**N)*2;

   initial
     begin
        $dumpfile("RCA_test.vcd");
        $dumpvars(0, RCA);
     end
    initial
    begin:apply_stimulus
        reg [N:0] ai,bi;
        reg [1:0] ci;
        for (ai=0; ai<2**N; ai=ai+1)
        begin
           for (bi=0; bi<2**N; bi=bi+1) 
           begin
               for (ci=0; ci<2; ci=ci+1)
               begin
                   a = ai;
                   b = bi;
                   cin = ci;
                 #10 $monitor("%d + %d + %d= %d %d", a, b, cin, cout,sum);

               end
           end
        end
    end

   RCA_4 RCA(a,b,cin,sum,cout);

endmodule

RCA/RCA_test.vcd
$date
	Thu Nov  5 20:34:36 2020
$end
$version
	Icarus Verilog
$end
$timescale
	1s
$end
$scope module RCA_4_tb $end
$scope module RCA $end
$var wire 4 ! a [3:0] $end
$var wire 4 " b [3:0] $end
$var wire 1 # cin $end
$var wire 4 $ sum [3:0] $end
$var wire 1 % cout $end
$scope module FA0 $end
$var wire 1 & a $end
$var wire 1 ' b $end
$var wire 1 # cin $end
$var wire 1 ( cout $end
$var wire 1 ) sum $end
$upscope $end
$scope module FA1 $end
$var wire 1 * a $end
$var wire 1 + b $end
$var wire 1 ( cin $end
$var wire 1 , cout $end
$var wire 1 - sum $end
$upscope $end
$scope module FA2 $end
$var wire 1 . a $end
$var wire 1 / b $end
$var wire 1 , cin $end
$var wire 1 0 cout $end
$var wire 1 1 sum $end
$upscope $end
$scope module FA3 $end
$var wire 1 2 a $end
$var wire 1 3 b $end
$var wire 1 0 cin $end
$var wire 1 % cout $end
$var wire 1 4 sum $end
$upscope $end
$upscope $end
$upscope $end
$enddefinitions $end
#0
$dumpvars
04
03
02
01
00
0/
0.
0-
0,
0+
0*
0)
0(
0'
0&
0%
b0 $
0#
b0 "
b0 !
$end
#10
b1 $
1)
1#
#20
1'
0#
b1 "
#30
1-
1(
b10 $
0)
1#
#40
01
0,
0(
b10 $
1-
0'
1+
0#
b10 "
#50
b11 $
1)
1#
#60
1'
0#
b11 "
#70
11
1,
0-
1(
b100 $
0)
1#
#80
04
0,
00
0(
0-
b100 $
11
0'
0+
1/
0#
b100 "
#90
b101 $
1)
1#
#100
1'
0#
b101 "
#110
1-
1(
b110 $
0)
1#
#120
04
00
11
0,
0(
b110 $
1-
0'
1+
0#
b110 "
#130
b111 $
1)
1#
#140
1'
0#
b111 "
#150
14
10
01
1,
0-
1(
b1000 $
0)
1#
#160
0,
00
0%
0(
0-
01
b1000 $
14
0'
0+
0/
13
0#
b1000 "
#170
b1001 $
1)
1#
#180
1'
0#
b1001 "
#190
1-
1(
b1010 $
0)
1#
#200
01
0,
0(
b1010 $
1-
0'
1+
0#
b1010 "
#210
b1011 $
1)
1#
#220
1'
0#
b1011 "
#230
11
1,
0-
1(
b1100 $
0)
1#
#240
0%
14
0,
00
0(
0-
b1100 $
11
0'
0+
1/
0#
b1100 "
#250
b1101 $
1)
1#
#260
1'
0#
b1101 "
#270
1-
1(
b1110 $
0)
1#
#280
0%
14
00
11
0,
0(
b1110 $
1-
0'
1+
0#
b1110 "
#290
b1111 $
1)
1#
#300
1'
0#
b1111 "
#310
1%
04
10
01
1,
0-
1(
b0 $
0)
1#
#320
0,
00
0%
0(
1)
0-
01
b1 $
04
0'
0+
0/
03
1&
0#
b0 "
b1 !
#330
1-
b10 $
0)
1(
1#
#340
b10 $
1-
1(
1'
0#
b1 "
#350
b11 $
1)
1#
#360
01
0,
0(
b11 $
1-
0'
1+
0#
b10 "
#370
11
1,
0-
b100 $
0)
1(
1#
#380
11
1,
b100 $
0-
1(
1'
0#
b11 "
#390
b101 $
1)
1#
#400
04
0,
00
0(
0-
b101 $
11
0'
0+
1/
0#
b100 "
#410
1-
b110 $
0)
1(
1#
#420
b110 $
1-
1(
1'
0#
b101 "
#430
b111 $
1)
1#
#440
04
00
11
0,
0(
b111 $
1-
0'
1+
0#
b110 "
#450
14
10
01
1,
0-
b1000 $
0)
1(
1#
#460
14
10
01
1,
b1000 $
0-
1(
1'
0#
b111 "
#470
b1001 $
1)
1#
#480
0,
00
0%
0(
0-
01
b1001 $
14
0'
0+
0/
13
0#
b1000 "
#490
1-
b1010 $
0)
1(
1#
#500
b1010 $
1-
1(
1'
0#
b1001 "
#510
b1011 $
1)
1#
#520
01
0,
0(
b1011 $
1-
0'
1+
0#
b1010 "
#530
11
1,
0-
b1100 $
0)
1(
1#
#540
11
1,
b1100 $
0-
1(
1'
0#
b1011 "
#550
b1101 $
1)
1#
#560
0%
14
0,
00
0(
0-
b1101 $
11
0'
0+
1/
0#
b1100 "
#570
1-
b1110 $
0)
1(
1#
#580
b1110 $
1-
1(
1'
0#
b1101 "
#590
b1111 $
1)
1#
#600
0%
14
00
11
0,
0(
b1111 $
1-
0'
1+
0#
b1110 "
#610
1%
04
10
01
1,
0-
b0 $
0)
1(
1#
#620
1%
04
10
01
1,
b0 $
0-
1(
1'
0#
b1111 "
#630
b1 $
1)
1#
#640
1-
0,
00
0%
0(
0)
01
b10 $
04
0'
0+
0/
03
0&
1*
0#
b0 "
b10 !
#650
b11 $
1)
1#
#660
1'
0#
b1 "
#670
11
0-
1,
1(
b100 $
0)
1#
#680
0(
b100 $
0-
0'
1+
0#
b10 "
#690
b101 $
1)
1#
#700
1'
0#
b11 "
#710
1-
1(
b110 $
0)
1#
#720
04
0,
00
0(
1-
b110 $
11
0'
0+
1/
0#
b100 "
#730
b111 $
1)
1#
#740
1'
0#
b101 "
#750
14
10
01
0-
1,
1(
b1000 $
0)
1#
#760
0(
b1000 $
0-
0'
1+
0#
b110 "
#770
b1001 $
1)
1#
#780
1'
0#
b111 "
#790
1-
1(
b1010 $
0)
1#
#800
0,
00
0%
0(
1-
01
b1010 $
14
0'
0+
0/
13
0#
b1000 "
#810
b1011 $
1)
1#
#820
1'
0#
b1001 "
#830
11
0-
1,
1(
b1100 $
0)
1#
#840
0(
b1100 $
0-
0'
1+
0#
b1010 "
#850
b1101 $
1)
1#
#860
1'
0#
b1011 "
#870
1-
1(
b1110 $
0)
1#
#880
0%
14
0,
00
0(
1-
b1110 $
11
0'
0+
1/
0#
b1100 "
#890
b1111 $
1)
1#
#900
1'
0#
b1101 "
#910
1%
04
10
01
0-
1,
1(
b0 $
0)
1#
#920
0(
b0 $
0-
0'
1+
0#
b1110 "
#930
b1 $
1)
1#
#940
1'
0#
b1111 "
#950
1-
1(
b10 $
0)
1#
#960
0,
00
0%
0(
1)
1-
01
b11 $
04
0'
0+
0/
03
1&
0#
b0 "
b11 !
#970
11
0-
1,
b100 $
0)
1(
1#
#980
11
b100 $
0-
1,
1(
1'
0#
b1 "
#990
b101 $
1)
1#
#1000
0(
b101 $
0-
0'
1+
0#
b10 "
#1010
1-
b110 $
0)
1(
1#
#1020
b110 $
1-
1(
1'
0#
b11 "
#1030
b111 $
1)
1#
#1040
04
0,
00
0(
1-
b111 $
11
0'
0+
1/
0#
b100 "
#1050
14
10
01
0-
1,
b1000 $
0)
1(
1#
#1060
14
10
01
b1000 $
0-
1,
1(
1'
0#
b101 "
#1070
b1001 $
1)
1#
#1080
0(
b1001 $
0-
0'
1+
0#
b110 "
#1090
1-
b1010 $
0)
1(
1#
#1100
b1010 $
1-
1(
1'
0#
b111 "
#1110
b1011 $
1)
1#
#1120
0,
00
0%
0(
1-
01
b1011 $
14
0'
0+
0/
13
0#
b1000 "
#1130
11
0-
1,
b1100 $
0)
1(
1#
#1140
11
b1100 $
0-
1,
1(
1'
0#
b1001 "
#1150
b1101 $
1)
1#
#1160
0(
b1101 $
0-
0'
1+
0#
b1010 "
#1170
1-
b1110 $
0)
1(
1#
#1180
b1110 $
1-
1(
1'
0#
b1011 "
#1190
b1111 $
1)
1#
#1200
0%
14
0,
00
0(
1-
b1111 $
11
0'
0+
1/
0#
b1100 "
#1210
1%
04
10
01
0-
1,
b0 $
0)
1(
1#
#1220
1%
04
10
01
b0 $
0-
1,
1(
1'
0#
b1101 "
#1230
b1 $
1)
1#
#1240
0(
b1 $
0-
0'
1+
0#
b1110 "
#1250
1-
b10 $
0)
1(
1#
#1260
b10 $
1-
1(
1'
0#
b1111 "
#1270
b11 $
1)
1#
#1280
11
00
0-
0%
0,
0(
0)
b100 $
04
0'
0+
0/
03
0&
0*
1.
0#
b0 "
b100 !
#1290
b101 $
1)
1#
#1300
1'
0#
b1 "
#1310
1-
1(
b110 $
0)
1#
#1320
04
11
00
0,
0(
b110 $
1-
0'
1+
0#
b10 "
#1330
b111 $
1)
1#
#1340
1'
0#
b11 "
#1350
14
01
10
1,
0-
1(
b1000 $
0)
1#
#1360
0,
0(
0-
b1000 $
01
0'
0+
1/
0#
b100 "
#1370
b1001 $
1)
1#
#1380
1'
0#
b101 "
#1390
1-
1(
b1010 $
0)
1#
#1400
01
0,
0(
b1010 $
1-
0'
1+
0#
b110 "
#1410
b1011 $
1)
1#
#1420
1'
0#
b111 "
#1430
11
1,
0-
1(
b1100 $
0)
1#
#1440
00
0,
0%
0(
0-
11
b1100 $
14
0'
0+
0/
13
0#
b1000 "
#1450
b1101 $
1)
1#
#1460
1'
0#
b1001 "
#1470
1-
1(
b1110 $
0)
1#
#1480
0%
14
11
00
0,
0(
b1110 $
1-
0'
1+
0#
b1010 "
#1490
b1111 $
1)
1#
#1500
1'
0#
b1011 "
#1510
1%
04
01
10
1,
0-
1(
b0 $
0)
1#
#1520
0,
0(
0-
b0 $
01
0'
0+
1/
0#
b1100 "
#1530
b1 $
1)
1#
#1540
1'
0#
b1101 "
#1550
1-
1(
b10 $
0)
1#
#1560
01
0,
0(
b10 $
1-
0'
1+
0#
b1110 "
#1570
b11 $
1)
1#
#1580
1'
0#
b1111 "
#1590
11
1,
0-
1(
b100 $
0)
1#
#1600
00
0,
0%
0(
1)
0-
11
b101 $
04
0'
0+
0/
03
1&
0#
b0 "
b101 !
#1610
1-
b110 $
0)
1(
1#
#1620
b110 $
1-
1(
1'
0#
b1 "
#1630
b111 $
1)
1#
#1640
04
11
00
0,
0(
b111 $
1-
0'
1+
0#
b10 "
#1650
14
01
10
1,
0-
b1000 $
0)
1(
1#
#1660
14
01
10
1,
b1000 $
0-
1(
1'
0#
b11 "
#1670
b1001 $
1)
1#
#1680
0,
0(
0-
b1001 $
01
0'
0+
1/
0#
b100 "
#1690
1-
b1010 $
0)
1(
1#
#1700
b1010 $
1-
1(
1'
0#
b101 "
#1710
b1011 $
1)
1#
#1720
01
0,
0(
b1011 $
1-
0'
1+
0#
b110 "
#1730
11
1,
0-
b1100 $
0)
1(
1#
#1740
11
1,
b1100 $
0-
1(
1'
0#
b111 "
#1750
b1101 $
1)
1#
#1760
00
0,
0%
0(
0-
11
b1101 $
14
0'
0+
0/
13
0#
b1000 "
#1770
1-
b1110 $
0)
1(
1#
#1780
b1110 $
1-
1(
1'
0#
b1001 "
#1790
b1111 $
1)
1#
#1800
0%
14
11
00
0,
0(
b1111 $
1-
0'
1+
0#
b1010 "
#1810
1%
04
01
10
1,
0-
b0 $
0)
1(
1#
#1820
1%
04
01
10
1,
b0 $
0-
1(
1'
0#
b1011 "
#1830
b1 $
1)
1#
#1840
0,
0(
0-
b1 $
01
0'
0+
1/
0#
b1100 "
#1850
1-
b10 $
0)
1(
1#
#1860
b10 $
1-
1(
1'
0#
b1101 "
#1870
b11 $
1)
1#
#1880
01
0,
0(
b11 $
1-
0'
1+
0#
b1110 "
#1890
11
1,
0-
b100 $
0)
1(
1#
#1900
11
1,
b100 $
0-
1(
1'
0#
b1111 "
#1910
b101 $
1)
1#
#1920
00
1-
0,
0%
0(
0)
11
b110 $
04
0'
0+
0/
03
0&
1*
0#
b0 "
b110 !
#1930
b111 $
1)
1#
#1940
1'
0#
b1 "
#1950
14
01
10
0-
1,
1(
b1000 $
0)
1#
#1960
0(
b1000 $
0-
0'
1+
0#
b10 "
#1970
b1001 $
1)
1#
#1980
1'
0#
b11 "
#1990
1-
1(
b1010 $
0)
1#
#2000
0,
0(
1-
b1010 $
01
0'
0+
1/
0#
b100 "
#2010
b1011 $
1)
1#
#2020
1'
0#
b101 "
#2030
11
0-
1,
1(
b1100 $
0)
1#
#2040
0(
b1100 $
0-
0'
1+
0#
b110 "
#2050
b1101 $
1)
1#
#2060
1'
0#
b111 "
#2070
1-
1(
b1110 $
0)
1#
#2080
00
0,
0%
0(
1-
11
b1110 $
14
0'
0+
0/
13
0#
b1000 "
#2090
b1111 $
1)
1#
#2100
1'
0#
b1001 "
#2110
1%
04
01
10
0-
1,
1(
b0 $
0)
1#
#2120
0(
b0 $
0-
0'
1+
0#
b1010 "
#2130
b1 $
1)
1#
#2140
1'
0#
b1011 "
#2150
1-
1(
b10 $
0)
1#
#2160
0,
0(
1-
b10 $
01
0'
0+
1/
0#
b1100 "
#2170
b11 $
1)
1#
#2180
1'
0#
b1101 "
#2190
11
0-
1,
1(
b100 $
0)
1#
#2200
0(
b100 $
0-
0'
1+
0#
b1110 "
#2210
b101 $
1)
1#
#2220
1'
0#
b1111 "
#2230
1-
1(
b110 $
0)
1#
#2240
00
0,
0%
0(
1)
1-
11
b111 $
04
0'
0+
0/
03
1&
0#
b0 "
b111 !
#2250
14
01
10
0-
1,
b1000 $
0)
1(
1#
#2260
14
01
10
b1000 $
0-
1,
1(
1'
0#
b1 "
#2270
b1001 $
1)
1#
#2280
0(
b1001 $
0-
0'
1+
0#
b10 "
#2290
1-
b1010 $
0)
1(
1#
#2300
b1010 $
1-
1(
1'
0#
b11 "
#2310
b1011 $
1)
1#
#2320
0,
0(
1-
b1011 $
01
0'
0+
1/
0#
b100 "
#2330
11
0-
1,
b1100 $
0)
1(
1#
#2340
11
b1100 $
0-
1,
1(
1'
0#
b101 "
#2350
b1101 $
1)
1#
#2360
0(
b1101 $
0-
0'
1+
0#
b110 "
#2370
1-
b1110 $
0)
1(
1#
#2380
b1110 $
1-
1(
1'
0#
b111 "
#2390
b1111 $
1)
1#
#2400
00
0,
0%
0(
1-
11
b1111 $
14
0'
0+
0/
13
0#
b1000 "
#2410
1%
04
01
10
0-
1,
b0 $
0)
1(
1#
#2420
1%
04
01
10
b0 $
0-
1,
1(
1'
0#
b1001 "
#2430
b1 $
1)
1#
#2440
0(
b1 $
0-
0'
1+
0#
b1010 "
#2450
1-
b10 $
0)
1(
1#
#2460
b10 $
1-
1(
1'
0#
b1011 "
#2470
b11 $
1)
1#
#2480
0,
0(
1-
b11 $
01
0'
0+
1/
0#
b1100 "
#2490
11
0-
1,
b100 $
0)
1(
1#
#2500
11
b100 $
0-
1,
1(
1'
0#
b1101 "
#2510
b101 $
1)
1#
#2520
0(
b101 $
0-
0'
1+
0#
b1110 "
#2530
1-
b110 $
0)
1(
1#
#2540
b110 $
1-
1(
1'
0#
b1111 "
#2550
b111 $
1)
1#
#2560
01
14
0%
0-
0,
00
0(
b1000 $
0)
0'
0+
0/
03
0&
0*
0.
12
0#
b0 "
b1000 !
#2570
b1001 $
1)
1#
#2580
1'
0#
b1 "
#2590
1-
1(
b1010 $
0)
1#
#2600
01
0,
0(
b1010 $
1-
0'
1+
0#
b10 "
#2610
b1011 $
1)
1#
#2620
1'
0#
b11 "
#2630
11
1,
0-
1(
b1100 $
0)
1#
#2640
14
0%
0,
00
0(
0-
b1100 $
11
0'
0+
1/
0#
b100 "
#2650
b1101 $
1)
1#
#2660
1'
0#
b101 "
#2670
1-
1(
b1110 $
0)
1#
#2680
14
0%
00
11
0,
0(
b1110 $
1-
0'
1+
0#
b110 "
#2690
b1111 $
1)
1#
#2700
1'
0#
b111 "
#2710
04
1%
10
01
1,
0-
1(
b0 $
0)
1#
#2720
0,
00
0(
0-
01
b0 $
04
0'
0+
0/
13
0#
b1000 "
#2730
b1 $
1)
1#
#2740
1'
0#
b1001 "
#2750
1-
1(
b10 $
0)
1#
#2760
01
0,
0(
b10 $
1-
0'
1+
0#
b1010 "
#2770
b11 $
1)
1#
#2780
1'
0#
b1011 "
#2790
11
1,
0-
1(
b100 $
0)
1#
#2800
04
0,
00
0(
0-
b100 $
11
0'
0+
1/
0#
b1100 "
#2810
b101 $
1)
1#
#2820
1'
0#
b1101 "
#2830
1-
1(
b110 $
0)
1#
#2840
04
00
11
0,
0(
b110 $
1-
0'
1+
0#
b1110 "
#2850
b111 $
1)
1#
#2860
1'
0#
b1111 "
#2870
14
10
01
1,
0-
1(
b1000 $
0)
1#
#2880
0%
0,
00
0(
1)
0-
01
b1001 $
14
0'
0+
0/
03
1&
0#
b0 "
b1001 !
#2890
1-
b1010 $
0)
1(
1#
#2900
b1010 $
1-
1(
1'
0#
b1 "
#2910
b1011 $
1)
1#
#2920
01
0,
0(
b1011 $
1-
0'
1+
0#
b10 "
#2930
11
1,
0-
b1100 $
0)
1(
1#
#2940
11
1,
b1100 $
0-
1(
1'
0#
b11 "
#2950
b1101 $
1)
1#
#2960
14
0%
0,
00
0(
0-
b1101 $
11
0'
0+
1/
0#
b100 "
#2970
1-
b1110 $
0)
1(
1#
#2980
b1110 $
1-
1(
1'
0#
b101 "
#2990
b1111 $
1)
1#
#3000
14
0%
00
11
0,
0(
b1111 $
1-
0'
1+
0#
b110 "
#3010
04
1%
10
01
1,
0-
b0 $
0)
1(
1#
#3020
04
1%
10
01
1,
b0 $
0-
1(
1'
0#
b111 "
#3030
b1 $
1)
1#
#3040
0,
00
0(
0-
01
b1 $
04
0'
0+
0/
13
0#
b1000 "
#3050
1-
b10 $
0)
1(
1#
#3060
b10 $
1-
1(
1'
0#
b1001 "
#3070
b11 $
1)
1#
#3080
01
0,
0(
b11 $
1-
0'
1+
0#
b1010 "
#3090
11
1,
0-
b100 $
0)
1(
1#
#3100
11
1,
b100 $
0-
1(
1'
0#
b1011 "
#3110
b101 $
1)
1#
#3120
04
0,
00
0(
0-
b101 $
11
0'
0+
1/
0#
b1100 "
#3130
1-
b110 $
0)
1(
1#
#3140
b110 $
1-
1(
1'
0#
b1101 "
#3150
b111 $
1)
1#
#3160
04
00
11
0,
0(
b111 $
1-
0'
1+
0#
b1110 "
#3170
14
10
01
1,
0-
b1000 $
0)
1(
1#
#3180
14
10
01
1,
b1000 $
0-
1(
1'
0#
b1111 "
#3190
b1001 $
1)
1#
#3200
0%
1-
0,
00
0(
0)
01
b1010 $
14
0'
0+
0/
03
0&
1*
0#
b0 "
b1010 !
#3210
b1011 $
1)
1#
#3220
1'
0#
b1 "
#3230
11
0-
1,
1(
b1100 $
0)
1#
#3240
0(
b1100 $
0-
0'
1+
0#
b10 "
#3250
b1101 $
1)
1#
#3260
1'
0#
b11 "
#3270
1-
1(
b1110 $
0)
1#
#3280
14
0%
0,
00
0(
1-
b1110 $
11
0'
0+
1/
0#
b100 "
#3290
b1111 $
1)
1#
#3300
1'
0#
b101 "
#3310
04
1%
10
01
0-
1,
1(
b0 $
0)
1#
#3320
0(
b0 $
0-
0'
1+
0#
b110 "
#3330
b1 $
1)
1#
#3340
1'
0#
b111 "
#3350
1-
1(
b10 $
0)
1#
#3360
0,
00
0(
1-
01
b10 $
04
0'
0+
0/
13
0#
b1000 "
#3370
b11 $
1)
1#
#3380
1'
0#
b1001 "
#3390
11
0-
1,
1(
b100 $
0)
1#
#3400
0(
b100 $
0-
0'
1+
0#
b1010 "
#3410
b101 $
1)
1#
#3420
1'
0#
b1011 "
#3430
1-
1(
b110 $
0)
1#
#3440
04
0,
00
0(
1-
b110 $
11
0'
0+
1/
0#
b1100 "
#3450
b111 $
1)
1#
#3460
1'
0#
b1101 "
#3470
14
10
01
0-
1,
1(
b1000 $
0)
1#
#3480
0(
b1000 $
0-
0'
1+
0#
b1110 "
#3490
b1001 $
1)
1#
#3500
1'
0#
b1111 "
#3510
1-
1(
b1010 $
0)
1#
#3520
0%
0,
00
0(
1)
1-
01
b1011 $
14
0'
0+
0/
03
1&
0#
b0 "
b1011 !
#3530
11
0-
1,
b1100 $
0)
1(
1#
#3540
11
b1100 $
0-
1,
1(
1'
0#
b1 "
#3550
b1101 $
1)
1#
#3560
0(
b1101 $
0-
0'
1+
0#
b10 "
#3570
1-
b1110 $
0)
1(
1#
#3580
b1110 $
1-
1(
1'
0#
b11 "
#3590
b1111 $
1)
1#
#3600
14
0%
0,
00
0(
1-
b1111 $
11
0'
0+
1/
0#
b100 "
#3610
04
1%
10
01
0-
1,
b0 $
0)
1(
1#
#3620
04
1%
10
01
b0 $
0-
1,
1(
1'
0#
b101 "
#3630
b1 $
1)
1#
#3640
0(
b1 $
0-
0'
1+
0#
b110 "
#3650
1-
b10 $
0)
1(
1#
#3660
b10 $
1-
1(
1'
0#
b111 "
#3670
b11 $
1)
1#
#3680
0,
00
0(
1-
01
b11 $
04
0'
0+
0/
13
0#
b1000 "
#3690
11
0-
1,
b100 $
0)
1(
1#
#3700
11
b100 $
0-
1,
1(
1'
0#
b1001 "
#3710
b101 $
1)
1#
#3720
0(
b101 $
0-
0'
1+
0#
b1010 "
#3730
1-
b110 $
0)
1(
1#
#3740
b110 $
1-
1(
1'
0#
b1011 "
#3750
b111 $
1)
1#
#3760
04
0,
00
0(
1-
b111 $
11
0'
0+
1/
0#
b1100 "
#3770
14
10
01
0-
1,
b1000 $
0)
1(
1#
#3780
14
10
01
b1000 $
0-
1,
1(
1'
0#
b1101 "
#3790
b1001 $
1)
1#
#3800
0(
b1001 $
0-
0'
1+
0#
b1110 "
#3810
1-
b1010 $
0)
1(
1#
#3820
b1010 $
1-
1(
1'
0#
b1111 "
#3830
b1011 $
1)
1#
#3840
0%
11
00
0-
0,
0(
0)
b1100 $
14
0'
0+
0/
03
0&
0*
1.
0#
b0 "
b1100 !
#3850
b1101 $
1)
1#
#3860
1'
0#
b1 "
#3870
1-
1(
b1110 $
0)
1#
#3880
14
0%
11
00
0,
0(
b1110 $
1-
0'
1+
0#
b10 "
#3890
b1111 $
1)
1#
#3900
1'
0#
b11 "
#3910
04
1%
01
10
1,
0-
1(
b0 $
0)
1#
#3920
0,
0(
0-
b0 $
01
0'
0+
1/
0#
b100 "
#3930
b1 $
1)
1#
#3940
1'
0#
b101 "
#3950
1-
1(
b10 $
0)
1#
#3960
01
0,
0(
b10 $
1-
0'
1+
0#
b110 "
#3970
b11 $
1)
1#
#3980
1'
0#
b111 "
#3990
11
1,
0-
1(
b100 $
0)
1#
#4000
00
0,
0(
0-
11
b100 $
04
0'
0+
0/
13
0#
b1000 "
#4010
b101 $
1)
1#
#4020
1'
0#
b1001 "
#4030
1-
1(
b110 $
0)
1#
#4040
04
11
00
0,
0(
b110 $
1-
0'
1+
0#
b1010 "
#4050
b111 $
1)
1#
#4060
1'
0#
b1011 "
#4070
14
01
10
1,
0-
1(
b1000 $
0)
1#
#4080
0,
0(
0-
b1000 $
01
0'
0+
1/
0#
b1100 "
#4090
b1001 $
1)
1#
#4100
1'
0#
b1101 "
#4110
1-
1(
b1010 $
0)
1#
#4120
01
0,
0(
b1010 $
1-
0'
1+
0#
b1110 "
#4130
b1011 $
1)
1#
#4140
1'
0#
b1111 "
#4150
11
1,
0-
1(
b1100 $
0)
1#
#4160
0%
00
0,
0(
1)
0-
11
b1101 $
14
0'
0+
0/
03
1&
0#
b0 "
b1101 !
#4170
1-
b1110 $
0)
1(
1#
#4180
b1110 $
1-
1(
1'
0#
b1 "
#4190
b1111 $
1)
1#
#4200
14
0%
11
00
0,
0(
b1111 $
1-
0'
1+
0#
b10 "
#4210
04
1%
01
10
1,
0-
b0 $
0)
1(
1#
#4220
04
1%
01
10
1,
b0 $
0-
1(
1'
0#
b11 "
#4230
b1 $
1)
1#
#4240
0,
0(
0-
b1 $
01
0'
0+
1/
0#
b100 "
#4250
1-
b10 $
0)
1(
1#
#4260
b10 $
1-
1(
1'
0#
b101 "
#4270
b11 $
1)
1#
#4280
01
0,
0(
b11 $
1-
0'
1+
0#
b110 "
#4290
11
1,
0-
b100 $
0)
1(
1#
#4300
11
1,
b100 $
0-
1(
1'
0#
b111 "
#4310
b101 $
1)
1#
#4320
00
0,
0(
0-
11
b101 $
04
0'
0+
0/
13
0#
b1000 "
#4330
1-
b110 $
0)
1(
1#
#4340
b110 $
1-
1(
1'
0#
b1001 "
#4350
b111 $
1)
1#
#4360
04
11
00
0,
0(
b111 $
1-
0'
1+
0#
b1010 "
#4370
14
01
10
1,
0-
b1000 $
0)
1(
1#
#4380
14
01
10
1,
b1000 $
0-
1(
1'
0#
b1011 "
#4390
b1001 $
1)
1#
#4400
0,
0(
0-
b1001 $
01
0'
0+
1/
0#
b1100 "
#4410
1-
b1010 $
0)
1(
1#
#4420
b1010 $
1-
1(
1'
0#
b1101 "
#4430
b1011 $
1)
1#
#4440
01
0,
0(
b1011 $
1-
0'
1+
0#
b1110 "
#4450
11
1,
0-
b1100 $
0)
1(
1#
#4460
11
1,
b1100 $
0-
1(
1'
0#
b1111 "
#4470
b1101 $
1)
1#
#4480
0%
00
1-
0,
0(
0)
11
b1110 $
14
0'
0+
0/
03
0&
1*
0#
b0 "
b1110 !
#4490
b1111 $
1)
1#
#4500
1'
0#
b1 "
#4510
04
1%
01
10
0-
1,
1(
b0 $
0)
1#
#4520
0(
b0 $
0-
0'
1+
0#
b10 "
#4530
b1 $
1)
1#
#4540
1'
0#
b11 "
#4550
1-
1(
b10 $
0)
1#
#4560
0,
0(
1-
b10 $
01
0'
0+
1/
0#
b100 "
#4570
b11 $
1)
1#
#4580
1'
0#
b101 "
#4590
11
0-
1,
1(
b100 $
0)
1#
#4600
0(
b100 $
0-
0'
1+
0#
b110 "
#4610
b101 $
1)
1#
#4620
1'
0#
b111 "
#4630
1-
1(
b110 $
0)
1#
#4640
00
0,
0(
1-
11
b110 $
04
0'
0+
0/
13
0#
b1000 "
#4650
b111 $
1)
1#
#4660
1'
0#
b1001 "
#4670
14
01
10
0-
1,
1(
b1000 $
0)
1#
#4680
0(
b1000 $
0-
0'
1+
0#
b1010 "
#4690
b1001 $
1)
1#
#4700
1'
0#
b1011 "
#4710
1-
1(
b1010 $
0)
1#
#4720
0,
0(
1-
b1010 $
01
0'
0+
1/
0#
b1100 "
#4730
b1011 $
1)
1#
#4740
1'
0#
b1101 "
#4750
11
0-
1,
1(
b1100 $
0)
1#
#4760
0(
b1100 $
0-
0'
1+
0#
b1110 "
#4770
b1101 $
1)
1#
#4780
1'
0#
b1111 "
#4790
1-
1(
b1110 $
0)
1#
#4800
0%
00
0,
0(
1)
1-
11
b1111 $
14
0'
0+
0/
03
1&
0#
b0 "
b1111 !
#4810
04
1%
01
10
0-
1,
b0 $
0)
1(
1#
#4820
04
1%
01
10
b0 $
0-
1,
1(
1'
0#
b1 "
#4830
b1 $
1)
1#
#4840
0(
b1 $
0-
0'
1+
0#
b10 "
#4850
1-
b10 $
0)
1(
1#
#4860
b10 $
1-
1(
1'
0#
b11 "
#4870
b11 $
1)
1#
#4880
0,
0(
1-
b11 $
01
0'
0+
1/
0#
b100 "
#4890
11
0-
1,
b100 $
0)
1(
1#
#4900
11
b100 $
0-
1,
1(
1'
0#
b101 "
#4910
b101 $
1)
1#
#4920
0(
b101 $
0-
0'
1+
0#
b110 "
#4930
1-
b110 $
0)
1(
1#
#4940
b110 $
1-
1(
1'
0#
b111 "
#4950
b111 $
1)
1#
#4960
00
0,
0(
1-
11
b111 $
04
0'
0+
0/
13
0#
b1000 "
#4970
14
01
10
0-
1,
b1000 $
0)
1(
1#
#4980
14
01
10
b1000 $
0-
1,
1(
1'
0#
b1001 "
#4990
b1001 $
1)
1#
#5000
0(
b1001 $
0-
0'
1+
0#
b1010 "
#5010
1-
b1010 $
0)
1(
1#
#5020
b1010 $
1-
1(
1'
0#
b1011 "
#5030
b1011 $
1)
1#
#5040
0,
0(
1-
b1011 $
01
0'
0+
1/
0#
b1100 "
#5050
11
0-
1,
b1100 $
0)
1(
1#
#5060
11
b1100 $
0-
1,
1(
1'
0#
b1101 "
#5070
b1101 $
1)
1#
#5080
0(
b1101 $
0-
0'
1+
0#
b1110 "
#5090
1-
b1110 $
0)
1(
1#
#5100
b1110 $
1-
1(
1'
0#
b1111 "
#5110
b1111 $
1)
1#
