RCA/FA.v
module FA (a,b,cin,sum,cout);
	input a, b, cin;
	output sum, cout;

	assign sum = cin ^ a ^ b; 
	assign cout = (a & b) | (b & cin) | (a & cin); 
endmodule

RCA/RCA_4.v
`include "FA.v"
module RCA_4 (a,b,cin,sum,cout);
	input [3:0] a, b; 
	input cin;
	output [3:0] sum; 
	output cout;
	wire w[2:0];
	FA	FA0(a[0],b[0],cin,sum[0],w[0]);
	FA	FA1(a[1],b[1],w[0],sum[1],w[1]);
	FA	FA2(a[2],b[1],w[1],sum[2],w[2]);
	FA	FA3(a[3],b[3],w[2],sum[3],cout);	
endmodule

RCA/RCA_4_tb_random.v
`include "RCA_4.v"
module RCA_4_tb;
parameter N=4;
reg [N-1:0] a, b;
reg cin,clock;
wire [N-1:0] sum; 
wire [N:0] k;
wire cout;
integer seed =1;
integer i =10000;
assign k = {cout,sum};
   initial
     begin
        $dumpfile("RCA_test.vcd");
        $dumpvars(0, RCA);
     end

initial
begin
clock = 0;
a=0;
b=0;
cin=0;
forever
#10 clock = ~clock;
end

initial
begin
repeat(i)@(negedge clock)
begin 
    cin= $random(seed) ; 
    a = $random(seed);
    b = $random(seed); 

    end
$finish;
end

initial 
begin
$monitor("%d + %d + %d= %d", a, b, cin, k);
if (a+b+cin != k) $display("ERROR");
end

RCA_4 RCA(a,b,cin,sum,cout);

endmodule

RCA/RCA_test.vcd
$date
	Thu Nov  5 21:19:15 2020
$end
$version
	Icarus Verilog
$end
$timescale
	1s
$end
$scope module RCA_4_tb $end
$scope module RCA $end
$var wire 4 ! a [3:0] $end
$var wire 4 " b [3:0] $end
$var wire 1 # cin $end
$var wire 4 $ sum [3:0] $end
$var wire 1 % cout $end
$scope module FA0 $end
$var wire 1 & a $end
$var wire 1 ' b $end
$var wire 1 # cin $end
$var wire 1 ( cout $end
$var wire 1 ) sum $end
$upscope $end
$scope module FA1 $end
$var wire 1 * a $end
$var wire 1 + b $end
$var wire 1 ( cin $end
$var wire 1 , cout $end
$var wire 1 - sum $end
$upscope $end
$scope module FA2 $end
$var wire 1 . a $end
$var wire 1 / b $end
$var wire 1 , cin $end
$var wire 1 0 cout $end
$var wire 1 1 sum $end
$upscope $end
$scope module FA3 $end
$var wire 1 2 a $end
$var wire 1 3 b $end
$var wire 1 0 cin $end
$var wire 1 % cout $end
$var wire 1 4 sum $end
$upscope $end
$upscope $end
$upscope $end
$enddefinitions $end
#0
$dumpvars
04
03
02
01
00
0/
0.
0-
0,
0+
0*
0)
0(
0'
0&
0%
b0 $
0#
b0 "
b0 !
$end
#20
14
1-
b1110 $
11
1+
1/
12
b110 "
b1000 !
#40
04
1%
1,
10
0-
11
b101 $
1)
1'
1*
1.
b111 "
b1110 !
#60
1-
1(
0)
01
b1010 $
14
0%
1&
0.
02
b11 "
b11 !
#80
1%
0-
04
b1 $
1)
0+
0/
13
1.
b1001 "
b111 !
1#
#100
0%
14
11
00
1-
0,
b1110 $
0)
0*
b1101 "
b101 !
0#
#120
10
1%
1,
14
11
b1110 $
0)
1+
1/
0&
1*
12
b1111 "
b1110 !
1#
#140
1%
10
1,
0-
01
1(
04
b0 $
0)
03
1&
0*
0.
b11 "
b1001 !
0#
#160
0,
1-
0(
1)
01
b1011 $
14
13
0&
1.
b1111 "
b1100 !
#180
04
00
0%
0)
1(
b10 $
1-
0'
0+
0/
03
1&
0.
02
b0 "
b1 !
1#
#200
1%
10
0-
1,
01
04
b1 $
1)
1'
1*
1.
12
b1 "
b1111 !
#220
1-
0,
14
0%
0(
01
00
b1011 $
1)
0&
0.
b101 "
b1010 !
0#
#240
1%
04
10
0-
1,
01
1(
b1 $
1)
13
1&
1.
02
b1001 "
b111 !
1#
#260
b0 $
0)
0'
b1100 "
#280
0%
14
0,
01
00
b1000 $
0)
0(
0&
0*
0.
b1000 "
b0 !
0#
#300
04
1%
10
1,
1(
0-
b0 $
01
1'
03
1*
1.
12
b101 "
b1110 !
1#
#320
1-
0,
1%
0(
b10 $
01
0'
1+
1/
13
0*
02
b1110 "
b100 !
0#
#340
00
04
0-
11
b101 $
1)
0+
0/
12
b1000 "
b1100 !
1#
#360
1,
0)
1(
0-
b100 $
11
1&
1*
0.
b1011 !
#380
14
10
0%
1,
1)
b1001 $
01
1'
1+
1/
03
0*
02
b111 "
b1 !
#400
1-
0,
0(
00
14
0%
b1011 $
01
0'
0+
0/
1*
12
b0 "
b1011 !
0#
#420
04
1%
10
0-
1,
0)
b0 $
01
1(
1'
0&
1.
b1 "
b1110 !
1#
#440
14
0%
0(
0-
0,
01
00
b1001 $
1)
0'
0*
0.
b0 "
b1000 !
#460
10
1,
1(
0-
01
b1001 $
14
1'
1&
1*
1.
02
b101 "
b111 !
#480
0%
0)
11
00
b1100 $
14
13
0&
0.
b1001 "
b10 !
#500
04
1%
10
0(
0-
b0 $
01
0'
1+
1/
03
12
b10 "
b1010 !
0#
#520
1(
0-
14
b1000 $
0)
0+
0/
13
1&
1.
b1100 "
b1111 !
1#
#540
04
0-
1,
b100 $
11
00
1(
1'
0.
b1101 "
b1011 !
0#
#560
14
10
b1110 $
1-
1+
1/
1.
b1011 "
b1111 !
#580
0-
0(
01
b0 $
04
0'
0&
0.
02
b1010 "
b10 !
#600
0%
14
0,
00
1-
b1010 $
01
0+
0/
b1100 "
#620
11
b1111 $
1)
1.
b1000 "
b110 !
1#
#640
1%
01
04
b11 $
1)
1&
0.
12
b1100 "
b1011 !
0#
#660
10
1,
1%
0)
0-
01
b0 $
04
1(
1'
1+
1/
03
0&
0*
b11 "
b1000 !
1#
#680
0,
1-
01
0(
14
b1011 $
1)
13
1.
b1011 "
b1100 !
0#
#700
1%
1(
1,
10
0)
1-
01
b10 $
04
03
1&
1*
0.
b11 "
b1011 !
#720
14
0%
0,
00
0(
1-
b1010 $
01
0'
0+
0/
0&
b0 "
b1010 !
#740
1%
1(
1-
11
04
b110 $
0)
13
1&
0*
1.
b1100 "
b1101 !
1#
#760
10
01
1,
1%
04
0-
b1 $
1)
0(
1+
1/
1*
0.
02
b1110 "
b11 !
0#
#780
11
00
0,
04
1-
b111 $
1)
0(
0+
0/
0&
1.
12
b1000 "
b1110 !
1#
#800
0%
b111 $
1)
03
1&
02
b100 "
b111 !
0#
#820
b101 $
0-
1'
0&
0*
b1 "
b100 !
#840
1%
10
01
1-
1,
04
1(
b11 $
1)
1+
1/
1&
1*
0.
12
b11 "
b1011 !
1#
#860
00
11
0,
0(
1-
b111 $
04
0%
0'
0&
0*
02
b110 "
b0 !
#880
1%
01
10
0-
1,
0)
1(
b0 $
04
0+
0/
1&
1*
1.
12
b0 "
b1111 !
#900
11
00
b100 $
04
0%
0.
02
b11 !
#920
04
1-
0,
1)
b111 $
11
00
0(
1'
0&
1.
b101 "
b110 !
0#
#940
14
10
01
1,
0)
1(
b1010 $
1-
0'
1+
1/
1&
0.
b10 "
b11 !
1#
#960
0-
00
0%
0,
1)
0(
01
b1001 $
14
0+
0/
13
0&
0*
b1000 "
b0 !
#980
10
1,
01
b1001 $
14
1'
1+
1/
03
1*
b111 "
b10 !
0#
#1000
1,
0)
0-
11
b100 $
04
1%
1(
0'
1&
0*
1.
12
b110 "
b1101 !
1#
#1020
1%
13
02
b1110 "
b101 !
#1040
1)
b1 $
01
0(
1'
0&
1*
0.
b1111 "
b10 !
0#
#1060
0%
14
00
1(
0-
11
b1100 $
0)
0+
0/
b1001 "
1#
#1080
10
1-
01
b1010 $
14
0'
1+
1/
03
1&
b110 "
b11 !
#1100
1%
0-
11
1)
b101 $
04
1'
13
0*
1.
b1111 "
b101 !
#1120
0%
01
14
0(
0,
00
b1001 $
0-
0'
0+
0/
0.
b1000 "
b1 !
0#
#1140
10
1,
0-
01
14
b1001 $
1)
0(
1+
1/
03
0&
1*
b10 "
b10 !
1#
#1160
1-
1(
11
b111 $
04
1%
1'
1&
1.
12
b11 "
b1111 !
#1180
01
0,
0(
0)
b10 $
1-
0'
0&
0*
b110 "
b1100 !
0#
#1200
b1010 $
14
00
0%
0+
0/
13
1*
0.
02
b1000 "
b10 !
#1220
10
1%
14
b1011 $
1)
1'
1+
1/
0*
1.
12
b1111 "
b1100 !
#1240
11
1,
0-
b101 $
04
0(
0'
1*
02
b1110 "
b110 !
1#
#1260
b1101 $
14
12
b1010 "
b1110 !
#1280
01
04
0,
00
b0 $
0)
0+
0/
0*
0.
b1000 "
b1000 !
0#
#1300
11
1,
1(
0%
b100 $
0-
1'
03
1&
1*
02
b101 "
b11 !
#1320
0%
0(
0-
0,
11
00
b1100 $
14
0'
13
0&
0*
1.
b1000 "
b100 !
#1340
04
1%
10
01
1,
b1 $
1)
1'
1+
1/
03
1*
0.
12
b11 "
b1010 !
#1360
1-
00
1(
0,
0)
04
0%
b10 $
01
0+
0/
1&
0*
02
b1 "
b1 !
#1380
0%
00
0,
0(
14
1-
b1110 $
11
0'
1+
1/
0&
12
b110 "
b1000 !
#1400
1,
0-
04
1%
1(
10
b100 $
11
1'
1.
b111 "
b1100 !
1#
#1420
01
14
0,
00
0%
1(
1-
b1010 $
0)
0+
0/
13
1&
0.
02
b1001 "
b1 !
0#
#1440
b1010 $
0)
03
0&
12
b1 "
b1000 !
1#
#1460
04
1%
10
1-
1,
1(
01
b10 $
0)
1+
1/
1&
1*
b111 "
b1011 !
0#
#1480
0-
14
0(
00
0,
0%
1)
b1001 $
01
0'
0+
0/
13
0*
02
b1000 "
b1 !
#1500
14
0%
00
0,
1-
11
b1111 $
1)
0(
1+
1/
03
0&
12
b10 "
b1000 !
1#
#1520
04
0-
b1 $
01
0+
0/
02
b100 "
b0 !
#1540
1%
b11 $
1-
13
1*
12
b1100 "
b1010 !
#1560
10
1,
1%
0-
01
b1 $
04
1'
1+
1/
03
b11 "
0#
#1580
14
00
0%
1(
0-
11
b1100 $
0)
0+
0/
13
02
b1101 "
b10 !
1#
#1600
1%
b100 $
04
12
b1001 "
b1010 !
#1620
01
1)
b1 $
0-
0,
0(
0'
1&
0*
b1000 "
b1001 !
0#
#1640
10
1,
1%
04
0-
01
b0 $
0)
1(
1+
1/
02
b1110 "
b1 !
1#
#1660
1,
0-
1(
11
b1100 $
14
1'
0&
1.
12
b1011 "
b1100 !
#1680
0%
01
1-
0,
00
b1010 $
14
0(
0'
0+
0/
1*
0.
02
b1100 "
b10 !
0#
#1700
11
b1111 $
1)
1'
1.
b1001 "
b110 !
#1720
1,
10
0)
0-
11
b1100 $
14
0'
1+
1/
03
b110 "
#1740
04
00
0,
1-
11
1%
b111 $
1)
1'
13
0*
0.
12
b1111 "
b1000 !
#1760
0%
1(
0)
1-
b1110 $
14
0+
0/
03
1&
1.
b101 "
b1101 !
#1780
0-
10
01
1%
0(
1)
1,
b1001 $
14
1+
1/
13
0&
1*
0.
b1111 "
b1010 !
#1800
04
0,
00
0%
1-
b11 $
01
0+
0/
03
02
b101 "
b10 !
#1820
0-
b1001 $
14
0*
12
b1 "
b1000 !
#1840
1-
0)
b1110 $
11
1(
0'
1&
1.
b100 "
b1101 !
1#
#1860
10
1,
1)
14
0-
b1101 $
11
0(
1'
1+
1/
0&
1*
02
b11 "
b110 !
0#
#1880
b101 $
04
1%
0'
1&
12
b110 "
b1111 !
#1900
14
0%
0-
01
b1000 $
0)
1(
0+
0/
02
b100 "
b111 !
1#
#1920
04
11
00
0,
b101 $
1)
0(
0*
b0 "
b101 !
0#
#1940
1,
11
14
b1100 $
0)
1(
13
1*
0.
b1100 "
b11 !
1#
#1960
1%
1-
0,
11
00
04
b111 $
1)
1'
0*
1.
12
b1101 "
b1101 !
#1980
14
10
0%
0)
1,
b1110 $
11
1+
1/
03
0&
1*
02
b11 "
b110 !
#2000
0-
b100 $
04
1%
0'
1&
0*
12
b10 "
b1101 !
#2020
00
0,
1-
11
04
b110 $
0)
0(
0+
0/
13
0&
1*
b1100 "
b1110 !
0#
#2040
1(
1-
01
b10 $
0)
1&
0*
0.
b1000 "
b1001 !
1#
#2060
10
0-
1,
1%
01
b0 $
04
1(
1'
03
1*
1.
b1 "
b1111 !
0#
#2080
1-
0,
0(
01
00
04
0%
b11 $
1)
0'
0.
02
b0 "
b11 !
#2100
11
1%
1,
10
04
b101 $
0-
1'
1+
1/
0&
1.
12
b111 "
b1110 !
#2120
00
1-
0,
1(
11
04
b110 $
0)
0+
0/
13
0*
b1101 "
b1100 !
1#
#2140
1,
10
1%
04
1(
0-
11
b100 $
0)
1+
1/
1&
02
b1011 "
b101 !
0#
#2160
1-
b110 $
0)
03
0&
1*
12
b111 "
b1110 !
1#
#2180
11
1,
00
04
0%
1(
0-
b100 $
0)
0+
0/
1&
0.
02
b101 "
b11 !
0#
#2200
1%
10
0(
1)
0-
01
b1 $
04
1+
1/
13
0&
b1011 "
b10 !
#2220
0%
11
b1101 $
14
0'
03
1&
1.
b10 "
b111 !
#2240
01
0,
1-
1%
b1011 $
1)
0(
13
0&
0*
12
b1010 "
b1100 !
1#
#2260
11
1,
0-
0%
b1100 $
0)
1(
03
1&
02
b110 "
b101 !
#2280
01
04
0,
00
1%
b10 $
1-
1(
1'
0+
0/
13
0.
12
b1001 "
b1001 !
0#
#2300
00
0,
0%
0(
1)
1-
11
b1111 $
14
1+
1/
03
0&
b111 "
b1000 !
#2340
1%
1,
10
1-
11
1(
14
b1110 $
0)
13
1*
1.
b1111 "
b1110 !
1#
#2360
04
00
0,
1)
0(
1-
b111 $
11
0'
0+
0/
1&
b1000 "
b1111 !
0#
#2380
14
10
01
1,
0-
b1001 $
1)
0(
1+
1/
0&
0.
b1010 "
b1010 !
1#
#2400
0,
0%
1-
b1011 $
01
03
0*
1.
02
b110 "
b100 !
#2420
0-
1,
10
1%
1(
01
b1 $
04
1'
0+
0/
13
1&
1*
b1001 "
b111 !
#2440
1%
01
04
1,
10
b0 $
0)
0'
1+
1/
0*
0.
b1010 "
b1 !
#2460
0%
14
0,
00
1-
b1010 $
01
1(
1'
0+
0/
b1101 "
0#
#2480
1%
01
04
0,
0(
10
1)
b11 $
1-
1+
1/
0&
1.
b1011 "
b100 !
#2500
0%
14
00
b1111 $
11
0'
1&
0.
b1010 "
b1 !
#2520
1%
04
10
01
1,
b1 $
0-
1(
1'
b1011 "
1#
#2540
b0 $
0)
03
0&
12
b11 "
b1000 !
#2560
0,
00
1-
01
b10 $
04
0+
0/
13
b1001 "
#2580
0-
0(
b1 $
1)
b1101 "
0#
#2600
10
1,
1%
04
b1 $
01
1+
1/
1*
02
b1111 "
b10 !
#2620
1,
0-
11
1(
b101 $
1)
03
1&
0*
1.
12
b111 "
b1101 !
1#
#2640
14
00
1-
0,
0(
0%
11
b1111 $
1)
0+
0/
13
0&
1*
02
b1101 "
b110 !
0#
#2660
1%
04
b110 $
0)
0'
12
b1000 "
b1110 !
#2680
0%
b10 $
01
03
0.
02
b100 "
b10 !
#2700
11
14
1,
10
1%
1)
b1101 $
0-
1'
1+
1/
13
1.
12
b1111 "
b1110 !
#2720
04
00
0,
0%
1-
b111 $
11
0'
03
1&
0*
0.
02
b10 "
b1 !
#2740
0-
1,
1(
1%
0)
b100 $
11
1'
0+
0/
13
1*
12
b1101 "
b1011 !
#2760
01
10
04
b1 $
1)
03
1.
b101 "
b1111 !
1#
#2780
11
00
0(
0)
0-
0,
b100 $
04
0%
0'
0&
0*
02
b0 "
b100 !
0#
#2800
1,
1)
1(
0-
11
b1101 $
14
1'
1&
1*
0.
12
b1 "
b1011 !
1#
#2820
01
1-
0,
1%
0(
04
b11 $
1)
13
0&
b1101 "
b1010 !
0#
#2840
0%
1-
11
1(
14
b1110 $
0)
03
0*
1.
b1 "
b1100 !
1#
#2860
1%
04
0,
10
0(
1-
01
b11 $
1)
1+
1/
13
02
b1011 "
b100 !
0#
#2880
1%
04
0-
1,
10
1(
0)
b0 $
01
0+
0/
1&
1*
b1001 "
b111 !
#2900
0%
1,
11
b1100 $
14
1+
1/
03
0*
b11 "
b101 !
#2920
04
00
0,
1%
1-
11
b111 $
1)
0+
0/
13
12
b1001 "
b1101 !
1#
#2940
b101 $
0-
0(
0%
0'
03
0&
02
b100 "
b100 !
#2960
1%
10
01
1,
1(
04
0)
b0 $
0-
1'
1+
1/
0.
12
b111 "
b1000 !
#2980
11
00
0,
04
0%
0(
0-
b101 $
1)
0+
0/
1.
02
b1 "
b100 !
0#
#3000
0%
00
11
0,
0(
1-
b1111 $
14
0'
1+
1/
13
0.
b1110 "
b0 !
1#
#3020
1%
1(
04
b111 $
1-
1'
0+
0/
1&
1.
12
b1101 "
b1101 !
#3040
14
01
10
0-
1,
b1000 $
0)
1*
b1001 "
b1111 !
0#
#3060
0%
11
00
14
b1100 $
0)
0&
0.
02
b10 !
1#
#3080
01
1-
0,
0(
b1011 $
1)
03
12
b1 "
b1010 !
0#
#3100
11
04
1%
1,
10
0)
1(
b110 $
1-
0'
1+
1/
1&
1.
b10 "
b1111 !
1#
#3120
1)
0-
b1 $
01
1'
0+
0/
b101 "
#3140
11
00
1-
0,
0(
0)
b110 $
04
0%
0'
0&
02
b0 "
b110 !
0#
#3160
0-
b1100 $
14
13
0*
b1100 "
b100 !
#3180
1-
1)
1(
b1011 $
01
1'
1&
0.
b1001 "
b1 !
1#
#3200
11
1,
10
1%
14
0)
b1100 $
0-
0'
1+
1/
1.
12
b1110 "
b1101 !
#3220
01
04
0,
00
1-
b11 $
1)
0(
0+
0/
1*
0.
b1000 "
b1011 !
0#
#3240
0)
b0 $
0-
0&
0*
b1100 "
b1000 !
#3260
1-
11
1(
1,
10
1%
b110 $
04
1'
1+
1/
1*
1.
02
b1111 "
b110 !
1#
#3280
14
0%
00
1-
0,
1(
11
b1110 $
0)
0+
0/
03
1&
0*
12
b101 "
b1101 !
0#
#3300
0%
14
00
11
0,
0(
1)
b1111 $
1-
1+
1/
13
0&
0.
02
b1011 "
b0 !
#3320
1%
04
01
10
0-
1,
1(
b0 $
0)
0+
0/
1&
1*
1.
b1001 "
b111 !
#3340
1-
0,
0(
01
00
04
b11 $
1)
0'
0.
12
b1100 "
b1011 !
#3360
10
1,
1%
0)
0-
01
b0 $
04
1(
1'
1+
1/
03
0&
0*
b11 "
b1000 !
1#
#3380
b1000 $
14
0'
13
1&
b1110 "
b1001 !
#3400
0%
11
00
0,
1)
0(
14
b1101 $
0-
0+
0/
0&
1.
02
b1100 "
b100 !
#3420
1-
b1111 $
1)
1+
1/
03
1&
0.
12
b10 "
b1001 !
0#
#3440
0)
b1010 $
01
0+
0/
0&
1*
b100 "
b1010 !
#3460
1%
11
04
1,
10
1)
1(
b111 $
1-
1'
1+
1/
13
1&
1.
02
b1011 "
b111 !
1#
#3480
14
0%
00
0,
0)
b1110 $
11
0'
0+
0/
03
0*
12
b0 "
b1101 !
#3500
1-
b110 $
04
1(
1'
02
b101 "
b101 !
0#
#3520
b110 $
0)
0&
b1 "
b100 !
1#
#3540
14
0,
10
1%
0(
1-
b1010 $
01
0'
1+
1/
13
12
b1010 "
b1100 !
0#
#3560
04
00
b110 $
11
0+
0/
1*
b1000 "
b1110 !
#3580
0%
1(
1-
01
14
b1010 $
0)
1&
0*
0.
02
b1100 "
b1 !
1#
#3600
11
1,
10
1%
14
b1110 $
1-
1(
1'
1+
1/
1*
1.
12
b1011 "
b1111 !
0#
#3620
04
00
0,
0(
1)
1-
b111 $
11
0+
0/
0&
b1101 "
b1110 !
#3640
1,
10
1%
04
1(
1-
11
b111 $
1)
1+
1/
1&
02
b1111 "
b111 !
1#
#3660
01
0,
00
04
b10 $
0)
0+
0/
0*
0.
12
b1101 "
b1001 !
0#
#3680
0-
0%
0(
1)
11
b1101 $
14
0'
03
0&
1.
b100 "
b1100 !
1#
#3700
1-
10
1%
1(
1,
0)
11
b1110 $
14
1'
1+
1/
13
1&
1*
b1111 "
b1111 !
0#
#3720
04
00
0,
0%
11
b111 $
1)
0+
0/
03
0*
02
b1 "
b101 !
1#
#3740
b11 $
01
0.
b1 !
#3760
11
0-
1,
b1101 $
14
13
1*
b1101 "
b11 !
#3780
01
1%
1-
0,
04
b10 $
0)
0*
12
b1001 "
b1001 !
0#
#3800
11
0%
0-
1,
14
b1101 $
1)
03
1*
b1 "
b1011 !
1#
#3820
01
0)
b1010 $
1-
0,
0&
0*
b1000 !
#3840
01
1)
b1011 $
1-
0,
0(
0'
1&
1*
b100 "
b1011 !
0#
#3860
0-
b1101 $
11
0*
1.
b1101 !
#3880
0-
01
10
1%
0)
1,
b1000 $
14
1(
1'
13
0&
1*
b1001 "
b1110 !
1#
#3900
0%
11
00
1-
0,
0(
b1110 $
14
0'
03
b0 "
0#
#3920
04
1%
10
01
1,
1)
b1 $
0-
1'
1+
1/
0.
b111 "
b1010 !
#3940
11
00
0,
04
0%
b100 $
0)
0'
0+
0/
0*
1.
02
b0 "
b100 !
#3960
1)
1-
b1111 $
14
1'
1+
1/
13
0.
b1011 "
b0 !
#3980
10
01
1,
1%
0-
b1001 $
14
0(
0'
1*
12
b1010 "
b1010 !
1#
#4000
04
0,
00
0%
1-
b11 $
01
1'
0+
0/
03
02
b101 "
b10 !
0#
#4020
11
14
1,
10
1(
1-
b1111 $
1)
1+
1/
1&
1.
b111 "
b111 !
1#
#4040
0-
0(
b101 $
04
1%
0'
12
b110 "
b1111 !
0#
#4060
01
0,
00
04
0%
0-
b1 $
1)
0(
0+
0/
0&
0*
0.
02
b0 "
b0 !
1#
#4080
14
10
1%
b1011 $
1-
1+
1/
13
1.
12
b1010 "
b1100 !
#4100
1%
0-
1,
1(
10
04
0)
b0 $
01
1'
0+
0/
1*
02
b1101 "
b110 !
#4120
1-
0(
0,
1)
b11 $
01
0'
1+
1/
0*
b1010 "
b100 !
#4140
00
04
b111 $
11
0+
0/
1*
12
b1000 "
b1110 !
#4160
0%
03
02
b0 "
b110 !
#4180
1%
01
10
0-
1,
1(
b1 $
04
1'
13
1&
b1101 "
b111 !
#4200
0%
14
11
00
0(
b1101 $
0-
0,
0'
0*
b1000 "
b101 !
0#
#4220
04
1%
10
b1 $
01
1,
1+
1/
03
1*
0.
12
b10 "
b1011 !
#4240
1%
13
02
b1010 "
b11 !
#4260
0%
1-
0)
11
b1110 $
14
1(
1'
03
0&
1.
b111 "
b110 !
1#
#4280
1%
1)
0-
01
b1 $
04
0+
0/
13
1&
b1101 "
b111 !
#4300
01
0%
0)
1,
10
b1000 $
14
1+
1/
03
0&
0*
0.
b111 "
b0 !
#4320
b1100 $
11
1.
b100 !
#4340
01
b0 $
04
1%
0.
12
b11 "
b1000 !
#4360
14
0(
0,
00
0%
1)
0-
b1001 $
01
0'
0+
0/
13
02
b1100 "
b0 !
#4380
10
1,
01
b1001 $
14
1+
1/
03
1*
b10 "
b10 !
#4400
04
1-
00
1(
0,
0)
1%
b10 $
01
1'
0+
0/
13
1&
0*
12
b1001 "
b1001 !
0#
#4420
01
0(
0%
1)
b11 $
1-
0,
0'
03
0&
1*
02
b0 "
b10 !
1#
#4440
14
10
1,
0-
1(
0)
b1000 $
01
1'
1+
1/
0*
b111 "
b0 !
#4460
b1100 $
11
1%
0'
13
1&
1.
12
b1110 "
b1101 !
#4480
1-
b110 $
04
1(
1'
03
1*
b111 "
b1111 !
0#
#4500
1%
0-
b0 $
01
0+
0/
13
02
b1101 "
b111 !
#4520
1-
11
b1110 $
14
0%
0(
0,
00
0'
1+
1/
03
0&
0*
0.
12
b110 "
b1000 !
#4540
1%
1(
1-
b110 $
04
1'
0+
0/
13
1&
1.
b1001 "
b1101 !
#4560
11
00
0%
0(
1-
0,
b1110 $
14
0'
03
0&
1*
b100 "
b1110 !
#4580
10
01
1(
1,
14
b1010 $
1-
1'
1+
1/
0.
02
b111 "
b10 !
1#
#4600
04
11
00
0,
0(
1%
1)
b111 $
1-
0'
0+
0/
13
1.
12
b1000 "
b1110 !
#4620
10
01
1,
1%
0-
04
b1 $
1)
1+
1/
03
1&
0.
b10 "
b1011 !
0#
#4640
b1001 $
14
0%
02
b11 !
#4660
1,
0-
0)
b1100 $
11
1%
1(
1'
13
0&
0*
1.
12
b1011 "
b1100 !
1#
#4680
1)
1-
b1011 $
01
1&
1*
0.
b1111 "
b1011 !
#4700
04
0-
b101 $
11
00
0(
0,
0'
0+
0/
0*
1.
b1100 "
b1101 !
0#
#4720
14
01
10
0%
1,
b1000 $
0)
1(
03
1*
02
b100 "
b111 !
1#
#4740
04
1-
b110 $
11
00
0,
1%
1(
1'
13
0*
12
b1101 "
b1101 !
0#
#4760
04
00
11
0,
0(
1)
b111 $
1-
0'
1+
1/
0&
0.
b1010 "
b1000 !
1#
#4780
10
01
1,
0-
1%
0)
1(
b0 $
04
03
1&
b10 "
b1001 !
#4800
11
00
0,
04
0%
1-
b110 $
0)
0(
0+
0/
0&
1*
1.
02
b0 "
b110 !
0#
#4820
1%
10
04
1)
b11 $
01
1'
1+
1/
0*
12
b111 "
b1100 !
#4840
14
0%
b1010 $
0)
0'
02
b10 "
b100 !
#4860
1%
1,
10
1)
1(
1-
01
b11 $
04
1'
13
1&
1*
0.
b1111 "
b11 !
1#
#4880
14
0%
11
00
0,
0(
0)
b1110 $
1-
0'
0+
0/
03
0&
1.
12
b100 "
b1110 !
0#
#4900
1%
04
10
01
1,
0-
1(
b0 $
0)
1+
1/
13
1&
0*
0.
02
b1110 "
b1 !
1#
#4920
14
0%
11
00
0,
1)
b1101 $
0-
0(
1'
0+
0/
03
0&
1.
12
b1 "
b1100 !
0#
#4940
1,
1(
0)
0-
b1100 $
11
1&
1*
0.
b1011 !
#4960
0(
1)
10
14
b1101 $
0-
1+
1/
0&
1.
02
b111 "
b110 !
#4980
14
10
1,
0-
01
1(
b1000 $
0)
0*
0.
b0 !
1#
#5000
1-
0,
0(
00
0%
1)
01
b1011 $
14
0'
0+
0/
13
1*
b1000 "
b10 !
#5020
0-
04
b0 $
0)
03
0*
b100 "
b0 !
0#
#5040
14
10
1-
b1011 $
1)
1+
1/
1.
b110 "
b100 !
1#
#5060
00
0%
0-
11
14
b1100 $
0)
0+
0/
13
b1000 "
0#
#5080
10
1,
11
b1100 $
14
1+
1/
03
1*
b110 "
b110 !
#5100
1%
1(
0-
01
04
b0 $
0)
0+
0/
13
1&
b1100 "
b111 !
1#
#5120
14
1)
1-
b1111 $
11
1'
1+
1/
12
b1011 "
b1111 !
#5140
0-
01
b1 $
04
0(
0,
00
0'
0+
0/
0*
0.
b1100 "
b1001 !
0#
#5160
14
10
1,
0%
0)
b1000 $
01
1+
1/
03
0&
1*
02
b110 "
b10 !
#5180
10
01
1%
1,
1)
1(
0-
b1 $
04
1'
13
1&
0*
b1111 "
b1 !
1#
#5200
0%
14
00
0)
b1100 $
11
0+
0/
0&
1*
b1001 "
b10 !
#5220
0-
10
1%
1,
14
1(
01
b1000 $
0)
1+
1/
1&
0*
12
b1011 "
b1001 !
0#
#5240
0%
0,
00
0(
1)
0-
01
b1001 $
14
0'
0+
0/
03
0&
b100 "
b1000 !
1#
#5260
1-
1(
0)
b10 $
04
1'
1&
02
b101 "
b1 !
0#
#5280
b0 $
0-
0(
1%
0'
13
0&
12
b1100 "
b1000 !
#5300
0%
1-
11
14
b1111 $
1)
1'
1*
1.
02
b1001 "
b110 !
#5320
10
1%
14
b1011 $
01
1+
1/
0*
12
b1011 "
b1100 !
#5340
11
1,
0-
0)
b100 $
04
0'
03
1*
b10 "
b1110 !
#5360
00
0,
1)
1-
11
b111 $
04
13
1&
0*
0.
b1010 "
b1001 !
#5380
0-
1,
1(
0)
b100 $
11
1'
0+
0/
1*
b1001 "
b1011 !
#5400
11
b1100 $
14
0%
1,
10
1+
1/
03
0*
1.
02
b11 "
b101 !
#5420
01
1-
0,
04
0(
00
b11 $
1)
1%
0'
0+
0/
13
0&
1*
0.
12
b1100 "
b1010 !
1#
#5440
0%
0-
11
b101 $
1)
03
1&
0*
1.
02
b0 "
b101 !
0#
#5460
1%
10
0)
1,
1-
11
b110 $
04
1(
1'
1+
1/
13
0&
1*
b1011 "
b110 !
1#
#5480
0%
14
0-
00
0(
0,
1)
b1101 $
11
0'
0+
0/
0*
b1000 "
b100 !
#5500
b101 $
04
1'
03
b101 "
0#
#5520
b111 $
1-
1*
b1 "
b110 !
#5540
1%
10
01
1,
04
b1 $
0-
0'
1+
1/
1&
0.
12
b110 "
b1011 !
#5560
0,
00
0)
1-
01
b10 $
04
0+
0/
13
0&
b1100 "
b1010 !
#5580
1%
10
1)
b11 $
04
1'
1+
1/
03
0*
1.
b111 "
b1100 !
#5600
14
0%
00
b1111 $
11
0'
1&
0.
b10 "
b1001 !
#5620
10
0-
01
1,
14
b1001 $
1)
0(
0&
1*
02
b10 !
1#
#5640
1-
0)
1(
b10 $
04
1%
1&
12
b110 "
b1011 !
#5660
11
00
0,
04
0%
0-
b100 $
0)
0(
0+
0/
0&
0*
1.
02
b0 "
b100 !
0#
#5680
14
10
1,
1%
1)
b1101 $
11
1+
1/
13
1&
1*
12
b1010 "
b1111 !
#5700
04
0-
b1 $
01
1(
1'
0+
0/
02
b1101 "
b111 !
1#
#5720
0%
14
11
00
1-
0,
b1110 $
0)
0'
0*
b1100 "
b101 !
#5740
1%
04
01
10
1(
b0 $
0-
1,
1'
0&
1*
b1101 "
b110 !
#5760
0-
0,
01
00
04
0(
b1 $
1)
0*
0.
12
b1000 !
0#
#5780
11
1,
14
1(
10
0)
b1100 $
0-
1+
1/
1&
1.
b1111 "
b1101 !
#5800
0%
00
14
b1101 $
1)
0+
0/
1*
0.
02
b1001 "
b11 !
1#
#5820
01
0(
0-
0,
b1 $
04
0'
03
0&
0*
b0 "
b0 !
#5840
1-
1(
0)
11
b1110 $
14
1'
13
1&
1.
b1001 "
b101 !
0#
#5860
0(
1)
1-
0,
b1011 $
01
0'
0&
1*
0.
b1100 "
b10 !
1#
